package/__init__.py
package/generate_password.py
packan/__init__.py
genUniquePassw-1.1.5.dist-info/METADATA
genUniquePassw-1.1.5.dist-info/WHEEL
genUniquePassw-1.1.5.dist-info/top_level.txt
genUniquePassw-1.1.5.dist-info/RECORD
