Metadata-Version: 2.1
Name: genUniquePassw
Version: 1.1.5
Summary: Python package to generate random passwords of maximum length 12, avoiding names present in specified files.
Home-page: https://github.com/kanchann23/genUniquePassw
Author: kanchan
Author-email: kanchanbora321@gmail.com
License: MIT
Keywords: security,password
Classifier: Development Status :: 5 - Production/Stable
Classifier: Intended Audience :: Developers
Classifier: License :: OSI Approved :: MIT License
Classifier: Programming Language :: Python :: 3
Classifier: Programming Language :: Python :: 3.7
Classifier: Programming Language :: Python :: 3.8
Classifier: Programming Language :: Python :: 3.9
